video2slides/__init__.py
video2slides/converter.py
video2slides/main.py
video2slides-0.1.0.dist-info/METADATA
video2slides-0.1.0.dist-info/WHEEL
video2slides-0.1.0.dist-info/entry_points.txt
video2slides-0.1.0.dist-info/RECORD
