Metadata-Version: 2.4
Name: video2slides
Version: 0.1.0
Summary: Convert video files to PowerPoint presentations with customizable frame extraction
Author-email: Anton Kulaga <antonkulaga@gmail.com>
License: MIT
Keywords: converter,powerpoint,pptx,presentation,slides,video
Classifier: Development Status :: 4 - Beta
Classifier: Intended Audience :: Developers
Classifier: License :: OSI Approved :: MIT License
Classifier: Programming Language :: Python :: 3
Classifier: Programming Language :: Python :: 3.11
Classifier: Programming Language :: Python :: 3.12
Classifier: Topic :: Multimedia :: Video
Classifier: Topic :: Office/Business
Requires-Python: >=3.11
Requires-Dist: eliot>=1.17.5
Requires-Dist: numpy<2.3.0,>=2.0.0
Requires-Dist: opencv-python>=4.12.0
Requires-Dist: pillow>=12.0.0
Requires-Dist: python-pptx>=1.0.2
Requires-Dist: scikit-image>=0.25.2
Requires-Dist: typer>=0.20.0
Requires-Dist: yt-dlp>=2025.10.22
Provides-Extra: dev
Requires-Dist: mypy>=1.18.2; extra == 'dev'
Requires-Dist: pytest-cov>=7.0.0; extra == 'dev'
Requires-Dist: pytest>=8.4.0; extra == 'dev'
Requires-Dist: ruff>=0.14.3; extra == 'dev'
Provides-Extra: gpu
Requires-Dist: opencv-contrib-python>=4.12.0; extra == 'gpu'
